uart.v
`default_nettype none 

module uart
#(
    parameter DELAY_FRAMES = 234 // 27,000,000 (27Mhz) / 115,200 Baud rate
    // such parameters can be changed by files that use this module! "local param configurable from outside"
)
(
    input clk,
    input uart_rx,
    output uart_tx,
    output reg [5:0] led,
    input btn1
);

localparam HALF_DELAY_WAIT = (DELAY_FRAMES / 2);

reg [3:0] rxState = 0; // track which state of receiver state machine
reg [12:0] rxCounter = 0; // count clock cycles
reg [2:0] rxBitNumber = 0; // track which bit we are reading/have read
reg [7:0] dataIn = 0; // store read-in data bits
reg byteReady = 0; // flag when reading in of data is finished, and dataIn can be used for other things
reg frameError = 0; // flag missing stop bit (warning because never read: read later)

// state machine states
localparam RX_STATE_IDLE = 0;
localparam RX_STATE_START_BIT = 1;
localparam RX_STATE_READ_WAIT = 2;
localparam RX_STATE_READ = 3;
localparam RX_STATE_STOP_BIT = 5;

always @(posedge clk) begin
    case (rxState)
        RX_STATE_IDLE: begin
            if (uart_rx == 0) begin
                rxState <= RX_STATE_START_BIT;
                rxCounter <= 1;
                rxBitNumber <= 0;
                byteReady <= 0; // reset counter, bitnumber, byteready and move to start bit state
                frameError <= 0; // reset possible frameError flag
            end
        end
        RX_STATE_START_BIT: begin
            if (rxCounter == HALF_DELAY_WAIT) begin
                rxState <= RX_STATE_READ_WAIT;
                rxCounter <= 1;
            end else
                rxCounter <= rxCounter + 1; //if we've waited half a frame, start waiting another half frame for reading, else increment clock
        end
        RX_STATE_READ_WAIT: begin
            rxCounter <= rxCounter + 1;
            if ((rxCounter + 1) == DELAY_FRAMES) begin
                rxState <= RX_STATE_READ; // check to equal delay frames because it should start counting at half delay frames (from start bit state)
            end
        end
        RX_STATE_READ: begin
            rxCounter <= 1; // reset counter
            dataIn <= {uart_rx, dataIn[7:1]}; // shift one databit in, concat uart_rx as MSB with top 7 bits in 8 bit dataIn! (shift register)
            rxBitNumber <= rxBitNumber + 1; // track which bit we are reading
            if (rxBitNumber == 3'b111)
                rxState <= RX_STATE_STOP_BIT;  // if bitnumber = 8 move to stop bit stait
            else
                rxState <= RX_STATE_READ_WAIT; // if not, start waiting for next bit (e.g. time the next reading)
        end
        RX_STATE_STOP_BIT: begin // note no framing error detection (it's not actually checking the stop bit!)
            rxCounter <= rxCounter + 1;
            if ((rxCounter + 1) == HALF_DELAY_WAIT) begin
                frameError <= (uart_rx != 1); // if stop bit not 1, assert
                byteReady <= (uart_rx == 1); // if stop bit 1 (correct), assert (otherwise byte is corrupt and not ready)
            end
            if ((rxCounter + 1) == HALF_DELAY_WAIT) begin
                rxState <= RX_STATE_IDLE; // after full frame: move back to idle
                rxCounter <= 0;
            end
        end
    endcase // special for case!
end

// check if we have some data and light up leds
always @(posedge clk) begin
    if (byteReady) begin
        led <= ~dataIn[5:0]; // negate as common anode
    end
end


// receiving

reg [3:0] txState = 0;
reg [24:0] txCounter = 0;
reg [7:0] dataOut = 0;
reg txPinRegister = 1; // stores current transmission value
reg [2:0] txBitNumber = 0;
reg [3:0] txByteCounter = 0; // track current byte we're sending (there's 12 bytes in the testMemory, so need to track)

assign uart_tx = txPinRegister;

localparam MEMORY_LENGTH = 12;
reg [7:0] testMemory [MEMORY_LENGTH-1:0]; // create 12 separate 8 bit registers!

// set memory
initial begin
    testMemory[0] = "Y";
    testMemory[1] = "o";
    testMemory[2] = "u";
    testMemory[3] = " ";
    testMemory[4] = "a";
    testMemory[5] = "r";
    testMemory[6] = "e";
    testMemory[7] = " ";
    testMemory[8] = "t";
    testMemory[9] = "i";
    testMemory[10] = "n";
    testMemory[11] = "y";
end

localparam TX_STATE_IDLE = 0;
localparam TX_STATE_START_BIT = 1;
localparam TX_STATE_WRITE = 2;
localparam TX_STATE_STOP_BIT = 3;
localparam TX_STATE_DEBOUNCE = 4; // debounce button

always @(posedge clk) begin
    case (txState)
        TX_STATE_IDLE: begin
            if (btn1 == 0) begin
                txState <= TX_STATE_START_BIT;
                txCounter <= 0;
                txByteCounter <= 0;
            end
            else begin
                txPinRegister <= 1; // keep line high if not transmitting
            end
        end
        TX_STATE_START_BIT: begin
            txPinRegister <= 0; // move line low to signal start of transmission (start bit)
            if ((txCounter + 1) == DELAY_FRAMES) begin // switch to transmit after a delay_frames period
                txState <= TX_STATE_WRITE;
                dataOut <= testMemory[txByteCounter]; // set dataOUt to appropriate byte of memory
                txBitNumber <= 0;
                txCounter <= 0;
            end
            else begin
                txCounter <= txCounter + 1;
            end
        end
        TX_STATE_WRITE: begin
            txPinRegister <= dataOut[txBitNumber]; // output appropriate bit of appropriate byte
            if ((txCounter + 1) == DELAY_FRAMES) begin // another delay frames after start bit state, to wait after the start bit signal
                if (txBitNumber == 3'b111) begin
                    txState <= TX_STATE_STOP_BIT;
                end else begin
                    txState <= TX_STATE_WRITE;
                    txBitNumber <= txBitNumber + 1; // write next bit, but only move to this state after delay!
                end
                txCounter <=0;
            end
            else begin
                txCounter <= txCounter + 1;
            end
        end
        TX_STATE_STOP_BIT: begin
            txPinRegister <= 1; // already waited in previous state so can instantly transmit stop bit
            if ((txCounter + 1) == DELAY_FRAMES) begin
                if (txByteCounter == MEMORY_LENGTH - 1) begin
                    txState <= TX_STATE_DEBOUNCE;
                end else begin
                    txByteCounter <= txByteCounter + 1; // next byte
                    txState <= TX_STATE_START_BIT; // new byte means start from start bit again
                end
                txCounter <= 0;
            end else begin
                txCounter <= txCounter + 1;
            end
        end
        TX_STATE_DEBOUNCE: begin // ensure one transmission for each button press, so check again only AFTER 10 ms ish (23 1s)
            if (txCounter == 23'b11111111111111111111111) begin
                if (btn1 == 1) begin
                    txState <= TX_STATE_IDLE;
                end
            end else begin
                txCounter <= txCounter + 1;
            end
        end
    endcase
end

endmodule

uart_tb.v
module test();
    reg clk = 0;
    reg uart_rx = 1;
    wire uart_tx;
    wire [5:0] led;
    reg btn = 1;
    // override delay frames, easier to look at only 8 clock pulses in simulation
    uart #(8'd8) u(
        clk,
        uart_rx,
        uart_tx,
        led,
        btn
    );

always
    #1 clk = ~clk; //#1 is iverilog simulation syntax; allows us to delay something by n time frames, toggles clock register every time unit to simulate clock

initial begin
    $display("Starting UART RX");
    $monitor("LED Value %b", led);
    #10 uart_rx=0; // start, delay 10 time frames
    #16 uart_rx=1; // delay 16 time frames, 8 clock cycles matches 8'd8
    #16 uart_rx=0;
    #16 uart_rx=0;
    #16 uart_rx=0;
    #16 uart_rx=0;
    #16 uart_rx=1;
    #16 uart_rx=1;
    #16 uart_rx=0;
  #1000 $finish;
end

initial begin
    $dumpfile("uart.vcd");
    $dumpvars(0,test);
end

endmodule
// doesn't receive any outside inputs, but creates all the inputs that the module we want to test requires, 
// then creates an instance of that module

uart.vcd
$date
	Tue Jun 23 18:04:50 2026
$end
$version
	Icarus Verilog
$end
$timescale
	1s
$end
$scope module test $end
$var wire 1 ! uart_tx $end
$var wire 6 " led [5:0] $end
$var reg 1 # btn $end
$var reg 1 $ clk $end
$var reg 1 % uart_rx $end
$scope module u $end
$var wire 1 # btn1 $end
$var wire 1 $ clk $end
$var wire 1 % uart_rx $end
$var wire 1 ! uart_tx $end
$var parameter 8 & DELAY_FRAMES $end
$var parameter 32 ' HALF_DELAY_WAIT $end
$var parameter 32 ( MEMORY_LENGTH $end
$var parameter 32 ) RX_STATE_IDLE $end
$var parameter 32 * RX_STATE_READ $end
$var parameter 32 + RX_STATE_READ_WAIT $end
$var parameter 32 , RX_STATE_START_BIT $end
$var parameter 32 - RX_STATE_STOP_BIT $end
$var parameter 32 . TX_STATE_DEBOUNCE $end
$var parameter 32 / TX_STATE_IDLE $end
$var parameter 32 0 TX_STATE_START_BIT $end
$var parameter 32 1 TX_STATE_STOP_BIT $end
$var parameter 32 2 TX_STATE_WRITE $end
$var reg 1 3 byteReady $end
$var reg 8 4 dataIn [7:0] $end
$var reg 8 5 dataOut [7:0] $end
$var reg 1 6 frameError $end
$var reg 6 7 led [5:0] $end
$var reg 3 8 rxBitNumber [2:0] $end
$var reg 13 9 rxCounter [12:0] $end
$var reg 4 : rxState [3:0] $end
$var reg 3 ; txBitNumber [2:0] $end
$var reg 4 < txByteCounter [3:0] $end
$var reg 25 = txCounter [24:0] $end
$var reg 1 > txPinRegister $end
$var reg 4 ? txState [3:0] $end
$upscope $end
$upscope $end
$enddefinitions $end
$comment Show the parameter values. $end
$dumpall
b10 2
b11 1
b1 0
b0 /
b100 .
b101 -
b1 ,
b10 +
b11 *
b0 )
b1100 (
b100 '
b1000 &
$end
#0
$dumpvars
b0 ?
1>
b0 =
b0 <
b0 ;
b0 :
b0 9
b0 8
bx 7
06
b0 5
b0 4
03
1%
0$
1#
bx "
1!
$end
#1
1$
#2
0$
#3
1$
#4
0$
#5
1$
#6
0$
#7
1$
#8
0$
#9
1$
#10
0$
0%
#11
b1 9
b1 :
1$
#12
0$
#13
b10 9
1$
#14
0$
#15
b11 9
1$
#16
0$
#17
b100 9
1$
#18
0$
#19
b1 9
b10 :
1$
#20
0$
#21
b10 9
1$
#22
0$
#23
b11 9
1$
#24
0$
#25
b100 9
1$
#26
0$
1%
#27
b101 9
1$
#28
0$
#29
b110 9
1$
#30
0$
#31
b111 9
1$
#32
0$
#33
b11 :
b1000 9
1$
#34
0$
#35
b10 :
b1 8
b10000000 4
b1 9
1$
#36
0$
#37
b10 9
1$
#38
0$
#39
b11 9
1$
#40
0$
#41
b100 9
1$
#42
0$
0%
#43
b101 9
1$
#44
0$
#45
b110 9
1$
#46
0$
#47
b111 9
1$
#48
0$
#49
b11 :
b1000 9
1$
#50
0$
#51
b10 :
b10 8
b1000000 4
b1 9
1$
#52
0$
#53
b10 9
1$
#54
0$
#55
b11 9
1$
#56
0$
#57
b100 9
1$
#58
0$
#59
b101 9
1$
#60
0$
#61
b110 9
1$
#62
0$
#63
b111 9
1$
#64
0$
#65
b11 :
b1000 9
1$
#66
0$
#67
b10 :
b11 8
b100000 4
b1 9
1$
#68
0$
#69
b10 9
1$
#70
0$
#71
b11 9
1$
#72
0$
#73
b100 9
1$
#74
0$
#75
b101 9
1$
#76
0$
#77
b110 9
1$
#78
0$
#79
b111 9
1$
#80
0$
#81
b11 :
b1000 9
1$
#82
0$
#83
b10 :
b100 8
b10000 4
b1 9
1$
#84
0$
#85
b10 9
1$
#86
0$
#87
b11 9
1$
#88
0$
#89
b100 9
1$
#90
0$
#91
b101 9
1$
#92
0$
#93
b110 9
1$
#94
0$
#95
b111 9
1$
#96
0$
#97
b11 :
b1000 9
1$
#98
0$
#99
b10 :
b101 8
b1000 4
b1 9
1$
#100
0$
#101
b10 9
1$
#102
0$
#103
b11 9
1$
#104
0$
#105
b100 9
1$
#106
0$
1%
#107
b101 9
1$
#108
0$
#109
b110 9
1$
#110
0$
#111
b111 9
1$
#112
0$
#113
b11 :
b1000 9
1$
#114
0$
#115
b10 :
b110 8
b10000100 4
b1 9
1$
#116
0$
#117
b10 9
1$
#118
0$
#119
b11 9
1$
#120
0$
#121
b100 9
1$
#122
0$
#123
b101 9
1$
#124
0$
#125
b110 9
1$
#126
0$
#127
b111 9
1$
#128
0$
#129
b11 :
b1000 9
1$
#130
0$
#131
b10 :
b111 8
b11000010 4
b1 9
1$
#132
0$
#133
b10 9
1$
#134
0$
#135
b11 9
1$
#136
0$
#137
b100 9
1$
#138
0$
0%
#139
b101 9
1$
#140
0$
#141
b110 9
1$
#142
0$
#143
b111 9
1$
#144
0$
#145
b11 :
b1000 9
1$
#146
0$
#147
b101 :
b0 8
b1100001 4
b1 9
1$
#148
0$
#149
b10 9
1$
#150
0$
#151
b11 9
1$
#152
0$
#153
b100 9
1$
#154
0$
#155
b101 9
1$
#156
0$
#157
b110 9
1$
#158
0$
#159
b111 9
1$
#160
0$
#161
b0 :
16
b0 9
1$
#162
0$
#163
06
b1 9
b1 :
1$
#164
0$
#165
b10 9
1$
#166
0$
#167
b11 9
1$
#168
0$
#169
b100 9
1$
#170
0$
#171
b1 9
b10 :
1$
#172
0$
#173
b10 9
1$
#174
0$
#175
b11 9
1$
#176
0$
#177
b100 9
1$
#178
0$
#179
b101 9
1$
#180
0$
#181
b110 9
1$
#182
0$
#183
b111 9
1$
#184
0$
#185
b11 :
b1000 9
1$
#186
0$
#187
b10 :
b1 8
b110000 4
b1 9
1$
#188
0$
#189
b10 9
1$
#190
0$
#191
b11 9
1$
#192
0$
#193
b100 9
1$
#194
0$
#195
b101 9
1$
#196
0$
#197
b110 9
1$
#198
0$
#199
b111 9
1$
#200
0$
#201
b11 :
b1000 9
1$
#202
0$
#203
b10 :
b10 8
b11000 4
b1 9
1$
#204
0$
#205
b10 9
1$
#206
0$
#207
b11 9
1$
#208
0$
#209
b100 9
1$
#210
0$
#211
b101 9
1$
#212
0$
#213
b110 9
1$
#214
0$
#215
b111 9
1$
#216
0$
#217
b11 :
b1000 9
1$
#218
0$
#219
b10 :
b11 8
b1100 4
b1 9
1$
#220
0$
#221
b10 9
1$
#222
0$
#223
b11 9
1$
#224
0$
#225
b100 9
1$
#226
0$
#227
b101 9
1$
#228
0$
#229
b110 9
1$
#230
0$
#231
b111 9
1$
#232
0$
#233
b11 :
b1000 9
1$
#234
0$
#235
b10 :
b100 8
b110 4
b1 9
1$
#236
0$
#237
b10 9
1$
#238
0$
#239
b11 9
1$
#240
0$
#241
b100 9
1$
#242
0$
#243
b101 9
1$
#244
0$
#245
b110 9
1$
#246
0$
#247
b111 9
1$
#248
0$
#249
b11 :
b1000 9
1$
#250
0$
#251
b10 :
b101 8
b11 4
b1 9
1$
#252
0$
#253
b10 9
1$
#254
0$
#255
b11 9
1$
#256
0$
#257
b100 9
1$
#258
0$
#259
b101 9
1$
#260
0$
#261
b110 9
1$
#262
0$
#263
b111 9
1$
#264
0$
#265
b11 :
b1000 9
1$
#266
0$
#267
b10 :
b110 8
b1 4
b1 9
1$
#268
0$
#269
b10 9
1$
#270
0$
#271
b11 9
1$
#272
0$
#273
b100 9
1$
#274
0$
#275
b101 9
1$
#276
0$
#277
b110 9
1$
#278
0$
#279
b111 9
1$
#280
0$
#281
b11 :
b1000 9
1$
#282
0$
#283
b10 :
b111 8
b0 4
b1 9
1$
#284
0$
#285
b10 9
1$
#286
0$
#287
b11 9
1$
#288
0$
#289
b100 9
1$
#290
0$
#291
b101 9
1$
#292
0$
#293
b110 9
1$
#294
0$
#295
b111 9
1$
#296
0$
#297
b11 :
b1000 9
1$
#298
0$
#299
b101 :
b0 8
b1 9
1$
#300
0$
#301
b10 9
1$
#302
0$
#303
b11 9
1$
#304
0$
#305
b100 9
1$
#306
0$
#307
b101 9
1$
#308
0$
#309
b110 9
1$
#310
0$
#311
b111 9
1$
#312
0$
#313
b0 :
16
b0 9
1$
#314
0$
#315
06
b1 9
b1 :
1$
#316
0$
#317
b10 9
1$
#318
0$
#319
b11 9
1$
#320
0$
#321
b100 9
1$
#322
0$
#323
b1 9
b10 :
1$
#324
0$
#325
b10 9
1$
#326
0$
#327
b11 9
1$
#328
0$
#329
b100 9
1$
#330
0$
#331
b101 9
1$
#332
0$
#333
b110 9
1$
#334
0$
#335
b111 9
1$
#336
0$
#337
b11 :
b1000 9
1$
#338
0$
#339
b10 :
b1 8
b1 9
1$
#340
0$
#341
b10 9
1$
#342
0$
#343
b11 9
1$
#344
0$
#345
b100 9
1$
#346
0$
#347
b101 9
1$
#348
0$
#349
b110 9
1$
#350
0$
#351
b111 9
1$
#352
0$
#353
b11 :
b1000 9
1$
#354
0$
#355
b10 :
b10 8
b1 9
1$
#356
0$
#357
b10 9
1$
#358
0$
#359
b11 9
1$
#360
0$
#361
b100 9
1$
#362
0$
#363
b101 9
1$
#364
0$
#365
b110 9
1$
#366
0$
#367
b111 9
1$
#368
0$
#369
b11 :
b1000 9
1$
#370
0$
#371
b10 :
b11 8
b1 9
1$
#372
0$
#373
b10 9
1$
#374
0$
#375
b11 9
1$
#376
0$
#377
b100 9
1$
#378
0$
#379
b101 9
1$
#380
0$
#381
b110 9
1$
#382
0$
#383
b111 9
1$
#384
0$
#385
b11 :
b1000 9
1$
#386
0$
#387
b10 :
b100 8
b1 9
1$
#388
0$
#389
b10 9
1$
#390
0$
#391
b11 9
1$
#392
0$
#393
b100 9
1$
#394
0$
#395
b101 9
1$
#396
0$
#397
b110 9
1$
#398
0$
#399
b111 9
1$
#400
0$
#401
b11 :
b1000 9
1$
#402
0$
#403
b10 :
b101 8
b1 9
1$
#404
0$
#405
b10 9
1$
#406
0$
#407
b11 9
1$
#408
0$
#409
b100 9
1$
#410
0$
#411
b101 9
1$
#412
0$
#413
b110 9
1$
#414
0$
#415
b111 9
1$
#416
0$
#417
b11 :
b1000 9
1$
#418
0$
#419
b10 :
b110 8
b1 9
1$
#420
0$
#421
b10 9
1$
#422
0$
#423
b11 9
1$
#424
0$
#425
b100 9
1$
#426
0$
#427
b101 9
1$
#428
0$
#429
b110 9
1$
#430
0$
#431
b111 9
1$
#432
0$
#433
b11 :
b1000 9
1$
#434
0$
#435
b10 :
b111 8
b1 9
1$
#436
0$
#437
b10 9
1$
#438
0$
#439
b11 9
1$
#440
0$
#441
b100 9
1$
#442
0$
#443
b101 9
1$
#444
0$
#445
b110 9
1$
#446
0$
#447
b111 9
1$
#448
0$
#449
b11 :
b1000 9
1$
#450
0$
#451
b101 :
b0 8
b1 9
1$
#452
0$
#453
b10 9
1$
#454
0$
#455
b11 9
1$
#456
0$
#457
b100 9
1$
#458
0$
#459
b101 9
1$
#460
0$
#461
b110 9
1$
#462
0$
#463
b111 9
1$
#464
0$
#465
b0 :
16
b0 9
1$
#466
0$
#467
06
b1 9
b1 :
1$
#468
0$
#469
b10 9
1$
#470
0$
#471
b11 9
1$
#472
0$
#473
b100 9
1$
#474
0$
#475
b1 9
b10 :
1$
#476
0$
#477
b10 9
1$
#478
0$
#479
b11 9
1$
#480
0$
#481
b100 9
1$
#482
0$
#483
b101 9
1$
#484
0$
#485
b110 9
1$
#486
0$
#487
b111 9
1$
#488
0$
#489
b11 :
b1000 9
1$
#490
0$
#491
b10 :
b1 8
b1 9
1$
#492
0$
#493
b10 9
1$
#494
0$
#495
b11 9
1$
#496
0$
#497
b100 9
1$
#498
0$
#499
b101 9
1$
#500
0$
#501
b110 9
1$
#502
0$
#503
b111 9
1$
#504
0$
#505
b11 :
b1000 9
1$
#506
0$
#507
b10 :
b10 8
b1 9
1$
#508
0$
#509
b10 9
1$
#510
0$
#511
b11 9
1$
#512
0$
#513
b100 9
1$
#514
0$
#515
b101 9
1$
#516
0$
#517
b110 9
1$
#518
0$
#519
b111 9
1$
#520
0$
#521
b11 :
b1000 9
1$
#522
0$
#523
b10 :
b11 8
b1 9
1$
#524
0$
#525
b10 9
1$
#526
0$
#527
b11 9
1$
#528
0$
#529
b100 9
1$
#530
0$
#531
b101 9
1$
#532
0$
#533
b110 9
1$
#534
0$
#535
b111 9
1$
#536
0$
#537
b11 :
b1000 9
1$
#538
0$
#539
b10 :
b100 8
b1 9
1$
#540
0$
#541
b10 9
1$
#542
0$
#543
b11 9
1$
#544
0$
#545
b100 9
1$
#546
0$
#547
b101 9
1$
#548
0$
#549
b110 9
1$
#550
0$
#551
b111 9
1$
#552
0$
#553
b11 :
b1000 9
1$
#554
0$
#555
b10 :
b101 8
b1 9
1$
#556
0$
#557
b10 9
1$
#558
0$
#559
b11 9
1$
#560
0$
#561
b100 9
1$
#562
0$
#563
b101 9
1$
#564
0$
#565
b110 9
1$
#566
0$
#567
b111 9
1$
#568
0$
#569
b11 :
b1000 9
1$
#570
0$
#571
b10 :
b110 8
b1 9
1$
#572
0$
#573
b10 9
1$
#574
0$
#575
b11 9
1$
#576
0$
#577
b100 9
1$
#578
0$
#579
b101 9
1$
#580
0$
#581
b110 9
1$
#582
0$
#583
b111 9
1$
#584
0$
#585
b11 :
b1000 9
1$
#586
0$
#587
b10 :
b111 8
b1 9
1$
#588
0$
#589
b10 9
1$
#590
0$
#591
b11 9
1$
#592
0$
#593
b100 9
1$
#594
0$
#595
b101 9
1$
#596
0$
#597
b110 9
1$
#598
0$
#599
b111 9
1$
#600
0$
#601
b11 :
b1000 9
1$
#602
0$
#603
b101 :
b0 8
b1 9
1$
#604
0$
#605
b10 9
1$
#606
0$
#607
b11 9
1$
#608
0$
#609
b100 9
1$
#610
0$
#611
b101 9
1$
#612
0$
#613
b110 9
1$
#614
0$
#615
b111 9
1$
#616
0$
#617
b0 :
16
b0 9
1$
#618
0$
#619
06
b1 9
b1 :
1$
#620
0$
#621
b10 9
1$
#622
0$
#623
b11 9
1$
#624
0$
#625
b100 9
1$
#626
0$
#627
b1 9
b10 :
1$
#628
0$
#629
b10 9
1$
#630
0$
#631
b11 9
1$
#632
0$
#633
b100 9
1$
#634
0$
#635
b101 9
1$
#636
0$
#637
b110 9
1$
#638
0$
#639
b111 9
1$
#640
0$
#641
b11 :
b1000 9
1$
#642
0$
#643
b10 :
b1 8
b1 9
1$
#644
0$
#645
b10 9
1$
#646
0$
#647
b11 9
1$
#648
0$
#649
b100 9
1$
#650
0$
#651
b101 9
1$
#652
0$
#653
b110 9
1$
#654
0$
#655
b111 9
1$
#656
0$
#657
b11 :
b1000 9
1$
#658
0$
#659
b10 :
b10 8
b1 9
1$
#660
0$
#661
b10 9
1$
#662
0$
#663
b11 9
1$
#664
0$
#665
b100 9
1$
#666
0$
#667
b101 9
1$
#668
0$
#669
b110 9
1$
#670
0$
#671
b111 9
1$
#672
0$
#673
b11 :
b1000 9
1$
#674
0$
#675
b10 :
b11 8
b1 9
1$
#676
0$
#677
b10 9
1$
#678
0$
#679
b11 9
1$
#680
0$
#681
b100 9
1$
#682
0$
#683
b101 9
1$
#684
0$
#685
b110 9
1$
#686
0$
#687
b111 9
1$
#688
0$
#689
b11 :
b1000 9
1$
#690
0$
#691
b10 :
b100 8
b1 9
1$
#692
0$
#693
b10 9
1$
#694
0$
#695
b11 9
1$
#696
0$
#697
b100 9
1$
#698
0$
#699
b101 9
1$
#700
0$
#701
b110 9
1$
#702
0$
#703
b111 9
1$
#704
0$
#705
b11 :
b1000 9
1$
#706
0$
#707
b10 :
b101 8
b1 9
1$
#708
0$
#709
b10 9
1$
#710
0$
#711
b11 9
1$
#712
0$
#713
b100 9
1$
#714
0$
#715
b101 9
1$
#716
0$
#717
b110 9
1$
#718
0$
#719
b111 9
1$
#720
0$
#721
b11 :
b1000 9
1$
#722
0$
#723
b10 :
b110 8
b1 9
1$
#724
0$
#725
b10 9
1$
#726
0$
#727
b11 9
1$
#728
0$
#729
b100 9
1$
#730
0$
#731
b101 9
1$
#732
0$
#733
b110 9
1$
#734
0$
#735
b111 9
1$
#736
0$
#737
b11 :
b1000 9
1$
#738
0$
#739
b10 :
b111 8
b1 9
1$
#740
0$
#741
b10 9
1$
#742
0$
#743
b11 9
1$
#744
0$
#745
b100 9
1$
#746
0$
#747
b101 9
1$
#748
0$
#749
b110 9
1$
#750
0$
#751
b111 9
1$
#752
0$
#753
b11 :
b1000 9
1$
#754
0$
#755
b101 :
b0 8
b1 9
1$
#756
0$
#757
b10 9
1$
#758
0$
#759
b11 9
1$
#760
0$
#761
b100 9
1$
#762
0$
#763
b101 9
1$
#764
0$
#765
b110 9
1$
#766
0$
#767
b111 9
1$
#768
0$
#769
b0 :
16
b0 9
1$
#770
0$
#771
06
b1 9
b1 :
1$
#772
0$
#773
b10 9
1$
#774
0$
#775
b11 9
1$
#776
0$
#777
b100 9
1$
#778
0$
#779
b1 9
b10 :
1$
#780
0$
#781
b10 9
1$
#782
0$
#783
b11 9
1$
#784
0$
#785
b100 9
1$
#786
0$
#787
b101 9
1$
#788
0$
#789
b110 9
1$
#790
0$
#791
b111 9
1$
#792
0$
#793
b11 :
b1000 9
1$
#794
0$
#795
b10 :
b1 8
b1 9
1$
#796
0$
#797
b10 9
1$
#798
0$
#799
b11 9
1$
#800
0$
#801
b100 9
1$
#802
0$
#803
b101 9
1$
#804
0$
#805
b110 9
1$
#806
0$
#807
b111 9
1$
#808
0$
#809
b11 :
b1000 9
1$
#810
0$
#811
b10 :
b10 8
b1 9
1$
#812
0$
#813
b10 9
1$
#814
0$
#815
b11 9
1$
#816
0$
#817
b100 9
1$
#818
0$
#819
b101 9
1$
#820
0$
#821
b110 9
1$
#822
0$
#823
b111 9
1$
#824
0$
#825
b11 :
b1000 9
1$
#826
0$
#827
b10 :
b11 8
b1 9
1$
#828
0$
#829
b10 9
1$
#830
0$
#831
b11 9
1$
#832
0$
#833
b100 9
1$
#834
0$
#835
b101 9
1$
#836
0$
#837
b110 9
1$
#838
0$
#839
b111 9
1$
#840
0$
#841
b11 :
b1000 9
1$
#842
0$
#843
b10 :
b100 8
b1 9
1$
#844
0$
#845
b10 9
1$
#846
0$
#847
b11 9
1$
#848
0$
#849
b100 9
1$
#850
0$
#851
b101 9
1$
#852
0$
#853
b110 9
1$
#854
0$
#855
b111 9
1$
#856
0$
#857
b11 :
b1000 9
1$
#858
0$
#859
b10 :
b101 8
b1 9
1$
#860
0$
#861
b10 9
1$
#862
0$
#863
b11 9
1$
#864
0$
#865
b100 9
1$
#866
0$
#867
b101 9
1$
#868
0$
#869
b110 9
1$
#870
0$
#871
b111 9
1$
#872
0$
#873
b11 :
b1000 9
1$
#874
0$
#875
b10 :
b110 8
b1 9
1$
#876
0$
#877
b10 9
1$
#878
0$
#879
b11 9
1$
#880
0$
#881
b100 9
1$
#882
0$
#883
b101 9
1$
#884
0$
#885
b110 9
1$
#886
0$
#887
b111 9
1$
#888
0$
#889
b11 :
b1000 9
1$
#890
0$
#891
b10 :
b111 8
b1 9
1$
#892
0$
#893
b10 9
1$
#894
0$
#895
b11 9
1$
#896
0$
#897
b100 9
1$
#898
0$
#899
b101 9
1$
#900
0$
#901
b110 9
1$
#902
0$
#903
b111 9
1$
#904
0$
#905
b11 :
b1000 9
1$
#906
0$
#907
b101 :
b0 8
b1 9
1$
#908
0$
#909
b10 9
1$
#910
0$
#911
b11 9
1$
#912
0$
#913
b100 9
1$
#914
0$
#915
b101 9
1$
#916
0$
#917
b110 9
1$
#918
0$
#919
b111 9
1$
#920
0$
#921
b0 :
16
b0 9
1$
#922
0$
#923
06
b1 9
b1 :
1$
#924
0$
#925
b10 9
1$
#926
0$
#927
b11 9
1$
#928
0$
#929
b100 9
1$
#930
0$
#931
b1 9
b10 :
1$
#932
0$
#933
b10 9
1$
#934
0$
#935
b11 9
1$
#936
0$
#937
b100 9
1$
#938
0$
#939
b101 9
1$
#940
0$
#941
b110 9
1$
#942
0$
#943
b111 9
1$
#944
0$
#945
b11 :
b1000 9
1$
#946
0$
#947
b10 :
b1 8
b1 9
1$
#948
0$
#949
b10 9
1$
#950
0$
#951
b11 9
1$
#952
0$
#953
b100 9
1$
#954
0$
#955
b101 9
1$
#956
0$
#957
b110 9
1$
#958
0$
#959
b111 9
1$
#960
0$
#961
b11 :
b1000 9
1$
#962
0$
#963
b10 :
b10 8
b1 9
1$
#964
0$
#965
b10 9
1$
#966
0$
#967
b11 9
1$
#968
0$
#969
b100 9
1$
#970
0$
#971
b101 9
1$
#972
0$
#973
b110 9
1$
#974
0$
#975
b111 9
1$
#976
0$
#977
b11 :
b1000 9
1$
#978
0$
#979
b10 :
b11 8
b1 9
1$
#980
0$
#981
b10 9
1$
#982
0$
#983
b11 9
1$
#984
0$
#985
b100 9
1$
#986
0$
#987
b101 9
1$
#988
0$
#989
b110 9
1$
#990
0$
#991
b111 9
1$
#992
0$
#993
b11 :
b1000 9
1$
#994
0$
#995
b10 :
b100 8
b1 9
1$
#996
0$
#997
b10 9
1$
#998
0$
#999
b11 9
1$
#1000
0$
#1001
b100 9
1$
#1002
0$
#1003
b101 9
1$
#1004
0$
#1005
b110 9
1$
#1006
0$
#1007
b111 9
1$
#1008
0$
#1009
b11 :
b1000 9
1$
#1010
0$
#1011
b10 :
b101 8
b1 9
1$
#1012
0$
#1013
b10 9
1$
#1014
0$
#1015
b11 9
1$
#1016
0$
#1017
b100 9
1$
#1018
0$
#1019
b101 9
1$
#1020
0$
#1021
b110 9
1$
#1022
0$
#1023
b111 9
1$
#1024
0$
#1025
b11 :
b1000 9
1$
#1026
0$
#1027
b10 :
b110 8
b1 9
1$
#1028
0$
#1029
b10 9
1$
#1030
0$
#1031
b11 9
1$
#1032
0$
#1033
b100 9
1$
#1034
0$
#1035
b101 9
1$
#1036
0$
#1037
b110 9
1$
#1038
0$
#1039
b111 9
1$
#1040
0$
#1041
b11 :
b1000 9
1$
#1042
0$
#1043
b10 :
b111 8
b1 9
1$
#1044
0$
#1045
b10 9
1$
#1046
0$
#1047
b11 9
1$
#1048
0$
#1049
b100 9
1$
#1050
0$
#1051
b101 9
1$
#1052
0$
#1053
b110 9
1$
#1054
0$
#1055
b111 9
1$
#1056
0$
#1057
b11 :
b1000 9
1$
#1058
0$
#1059
b101 :
b0 8
b1 9
1$
#1060
0$
#1061
b10 9
1$
#1062
0$
#1063
b11 9
1$
#1064
0$
#1065
b100 9
1$
#1066
0$
#1067
b101 9
1$
#1068
0$
#1069
b110 9
1$
#1070
0$
#1071
b111 9
1$
#1072
0$
#1073
b0 :
16
b0 9
1$
#1074
0$
#1075
06
b1 9
b1 :
1$
#1076
0$
#1077
b10 9
1$
#1078
0$
#1079
b11 9
1$
#1080
0$
#1081
b100 9
1$
#1082
0$
#1083
b1 9
b10 :
1$
#1084
0$
#1085
b10 9
1$
#1086
0$
#1087
b11 9
1$
#1088
0$
#1089
b100 9
1$
#1090
0$
#1091
b101 9
1$
#1092
0$
#1093
b110 9
1$
#1094
0$
#1095
b111 9
1$
#1096
0$
#1097
b11 :
b1000 9
1$
#1098
0$
#1099
b10 :
b1 8
b1 9
1$
#1100
0$
#1101
b10 9
1$
#1102
0$
#1103
b11 9
1$
#1104
0$
#1105
b100 9
1$
