uart.v
`default_nettype none 

module uart
#(
    parameter ACC_INCREMENT = 3,
    parameter ACC_MODULUS = 8,
    parameter BAUD_DIVISOR = 234,
    parameter PARITY_ODD = 0 // to set parity odd or even
    // such parameters can be changed by files that use this module! "local param configurable from outside"
)
(
    input clk,
    input uart_rx,
    output uart_tx,
    output reg [5:0] led,
    input btn1
);


localparam HALF_DELAY_WAIT = BAUD_DIVISOR / 2; // same for 234 or 235

reg [3:0] rxState = 0; // track which state of receiver state machine
reg [12:0] rxCounter = 0; // count clock cycles
reg [2:0] rxBitNumber = 0; // track which bit we are reading/have read
reg [7:0] dataIn = 0; // store read-in data bits
reg byteReady = 0; // flag when reading in of data is finished, and dataIn can be used for other things
reg frameError = 0; // flag missing stop bit (warning because never read: read later)
reg parityError = 0;

reg [$clog2(ACC_MODULUS):0] rxAccumulator = 0; // $clog2 is a Verilog system function that computes the ceiling log base 2 of a value - compile time
reg [12:0] rxDelayFrames = BAUD_DIVISOR;

// state machine states
localparam RX_STATE_IDLE = 0;
localparam RX_STATE_START_BIT = 1;
localparam RX_STATE_READ_WAIT = 2;
localparam RX_STATE_READ = 3;
localparam RX_STATE_PARITY_BIT = 4;
localparam RX_STATE_STOP_BIT = 5;

always @(posedge clk) begin
    case (rxState)
        RX_STATE_IDLE: begin
            if (uart_rx == 0) begin
                rxState <= RX_STATE_START_BIT;
                rxCounter <= 1;
                rxBitNumber <= 0;
                byteReady <= 0; // reset counter, bitnumber, byteready and move to start bit state
                frameError <= 0; // reset possible frameError flag
                parityError <= 0; // reset possible parityError flag
            end
        end
        RX_STATE_START_BIT: begin
            if (rxCounter == HALF_DELAY_WAIT) begin
                rxState <= RX_STATE_READ_WAIT;
                rxCounter <= 1;
            end else begin
                rxCounter <= rxCounter + 1; //if we've waited half a frame, start waiting another half frame for reading, else increment clock
            end
        end
        RX_STATE_READ_WAIT: begin
            rxCounter <= rxCounter + 1;
            if ((rxCounter + 1) == rxDelayFrames) begin
                rxState <= RX_STATE_READ; // check to equal delay frames because it should start counting at half delay frames (from start bit state)
                // update accumulator
                if ((rxAccumulator + ACC_INCREMENT) >= ACC_MODULUS) begin
                    rxDelayFrames <= BAUD_DIVISOR + 1;
                    rxAccumulator <= rxAccumulator + ACC_INCREMENT - ACC_MODULUS;
                end else begin
                    rxDelayFrames <= BAUD_DIVISOR;
                    rxAccumulator <= rxAccumulator + ACC_INCREMENT;
                end
            end
        end
        RX_STATE_READ: begin
            rxCounter <= 1; // reset counter
            dataIn <= {uart_rx, dataIn[7:1]}; // shift one databit in, concat uart_rx as MSB with top 7 bits in 8 bit dataIn! (shift register)
            rxBitNumber <= rxBitNumber + 1; // track which bit we are reading
            if (rxBitNumber == 3'b111)
                rxState <= RX_STATE_PARITY_BIT;  // if bitnumber = 8 move to parity bit state
            else
                rxState <= RX_STATE_READ_WAIT; // if not, start waiting for next bit (e.g. time the next reading)
        end
        RX_STATE_PARITY_BIT: begin
            rxCounter <= rxCounter + 1;
            if ((rxCounter + 1) == rxDelayFrames) begin
                parityError <= ^{dataIn, uart_rx} ^ PARITY_ODD; // for even parity check: xor everything, if even this is 0 (no error), else 1 (error)
                rxState <= RX_STATE_STOP_BIT;
                rxCounter <= 0;
                // update accumulator
                if ((rxAccumulator + ACC_INCREMENT) >= ACC_MODULUS) begin
                    rxDelayFrames <= BAUD_DIVISOR + 1;
                    rxAccumulator <= rxAccumulator + ACC_INCREMENT - ACC_MODULUS;
                end else begin
                    rxDelayFrames <= BAUD_DIVISOR;
                    rxAccumulator <= rxAccumulator + ACC_INCREMENT;
                end
            end
        end
        RX_STATE_STOP_BIT: begin 
            rxCounter <= rxCounter + 1;
            if ((rxCounter + 1) == rxDelayFrames) begin // read ends in middle of frame, so wait one full frame to land in next middle
                frameError <= (uart_rx != 1); // if stop bit not 1, assert
                byteReady <= (uart_rx == 1) && !parityError; // assert if stop bit correct and no parityError
                rxState <= RX_STATE_IDLE; // after full frame: move back to idle
                rxCounter <= 0;
                // update accumulator
                if ((rxAccumulator + ACC_INCREMENT) >= ACC_MODULUS) begin
                    rxDelayFrames <= BAUD_DIVISOR + 1;
                    rxAccumulator <= rxAccumulator + ACC_INCREMENT - ACC_MODULUS;
                end else begin
                    rxDelayFrames <= BAUD_DIVISOR;
                    rxAccumulator <= rxAccumulator + ACC_INCREMENT;
                end
            end
        end
    endcase // special for case!
end

// check if we have some data and light up leds
always @(posedge clk) begin
    if (byteReady) begin
        led <= ~dataIn[5:0]; // negate as common anode
    end
    led[5] <= ~frameError;
    led[6] <= ~parityError;
end


// transmitting

reg [3:0] txState = 0;
reg [24:0] txCounter = 0;
reg [7:0] dataOut = 0;
reg txPinRegister = 1; // stores current transmission value
reg [2:0] txBitNumber = 0;
reg [3:0] txByteCounter = 0; // track current byte we're sending (there's 12 bytes in the testMemory, so need to track)

reg txEchoMode = 0;
reg byteConsumed = 0;

assign uart_tx = txPinRegister;

localparam MEMORY_LENGTH = 12;
reg [7:0] testMemory [MEMORY_LENGTH-1:0]; // create 12 separate 8 bit registers!

// set memory
initial begin
    testMemory[0] = "H";
    testMemory[1] = "e";
    testMemory[2] = "y";
    testMemory[3] = " ";
    testMemory[4] = "t";
    testMemory[5] = "h";
    testMemory[6] = "e";
    testMemory[7] = "r";
    testMemory[8] = "e";
    testMemory[9] = "!";
    testMemory[10] = "!";
    testMemory[11] = "!";
end

localparam TX_STATE_IDLE = 0;
localparam TX_STATE_START_BIT = 1;
localparam TX_STATE_WRITE = 2;
localparam TX_STATE_PARITY_BIT = 3;
localparam TX_STATE_STOP_BIT = 4;
localparam TX_STATE_DEBOUNCE = 5; // debounce button

reg byteReadyPrev = 0;
always @(posedge clk) begin
    byteReadyPrev <= byteReady; // load value of byte ready in current clock cycle into byteReadyPrev: edge detection
end

always @(posedge clk) begin
    if (byteReady && !byteReadyPrev) begin
        byteConsumed <= 0;
    end
    case (txState)
        TX_STATE_IDLE: begin
            if (btn1 == 0) begin
                txEchoMode <= 0;
                txState <= TX_STATE_START_BIT;
                txCounter <= 0;
                txByteCounter <= 0;
            end
            else if (byteReady && !byteConsumed) begin
                byteConsumed <= 1;
                txEchoMode <= 1;
                txState <= TX_STATE_START_BIT;
                dataOut <= dataIn;
                txCounter <= 0;
            end
            else begin
                txPinRegister <= 1; // keep line high if not transmitting
            end
        end
        TX_STATE_START_BIT: begin
            txPinRegister <= 0; // move line low to signal start of transmission (start bit)
            if ((txCounter + 1) == DELAY_FRAMES) begin // switch to transmit after a delay_frames period
                txState <= TX_STATE_WRITE;
                if (!txEchoMode) begin
                    dataOut <= testMemory[txByteCounter]; // set dataOUt to appropriate byte of memory
                end // else dataIn in dataOut
                txBitNumber <= 0;
                txCounter <= 0;
            end
            else begin
                txCounter <= txCounter + 1;
            end
        end
        TX_STATE_WRITE: begin
            txPinRegister <= dataOut[txBitNumber]; // output appropriate bit of appropriate byte
            if ((txCounter + 1) == DELAY_FRAMES) begin // another delay frames after start bit state, to wait after the start bit signal
                if (txBitNumber == 3'b111) begin
                    txState <= TX_STATE_PARITY_BIT;
                end else begin
                    txState <= TX_STATE_WRITE;
                    txBitNumber <= txBitNumber + 1; // write next bit, but only move to this state after delay!
                end
                txCounter <=0;
            end
            else begin
                txCounter <= txCounter + 1;
            end
        end
        TX_STATE_PARITY_BIT: begin
            txPinRegister <= ^dataOut ^ PARITY_ODD; // even parity; if uneven 1s this is 1, so adds the one bit to make total even
            if ((txCounter + 1) == DELAY_FRAMES) begin
                txState <= TX_STATE_STOP_BIT;
                txCounter <= 0;
            end
            else begin
                txCounter <= txCounter + 1;
            end
        end
        TX_STATE_STOP_BIT: begin
            txPinRegister <= 1; // already waited in previous state so can instantly transmit stop bit
            if ((txCounter + 1) == DELAY_FRAMES) begin
                if (txEchoMode) begin
                    txEchoMode <= 0;
                    txState <= TX_STATE_IDLE; // no need to debounce when mirroring
                end
                else if (txByteCounter == MEMORY_LENGTH - 1) begin
                    txState <= TX_STATE_DEBOUNCE;
                end else begin
                    txByteCounter <= txByteCounter + 1; // next byte
                    txState <= TX_STATE_START_BIT; // new byte means start from start bit again
                end
                txCounter <= 0;
            end else begin
                txCounter <= txCounter + 1;
            end
        end
        TX_STATE_DEBOUNCE: begin // ensure one transmission for each button press, so check again only AFTER 10 ms ish (23 1s)
            if (txCounter == 23'b11111111111111111111111) begin
                if (btn1 == 1) begin
                    txState <= TX_STATE_IDLE;
                end
            end else begin
                txCounter <= txCounter + 1;
            end
        end
    endcase
end

endmodule

uart_tb.v
module test();
    reg clk = 0;
    reg uart_rx = 1;
    wire uart_tx;
    wire [5:0] led;
    reg btn = 1;
    // override delay frames, easier to look at only 8 clock pulses in simulation
    uart #(8'd8) u(
        clk,
        uart_rx,
        uart_tx,
        led,
        btn
    );

always
    #1 clk = ~clk; //#1 is iverilog simulation syntax; allows us to delay something by n time frames, toggles clock register every time unit to simulate clock

initial begin
    $display("Starting UART RX");
    $monitor("LED Value %b", led);
    #10 uart_rx=0; // start, delay 10 time frames
    #16 uart_rx=1; // delay 16 time frames, 8 clock cycles matches 8'd8
    #16 uart_rx=0;
    #16 uart_rx=0;
    #16 uart_rx=0;
    #16 uart_rx=0;
    #16 uart_rx=1;
    #16 uart_rx=1;
    #16 uart_rx=0;
    #16 uart_rx=1; // stop
  #1000 $finish;
end

initial begin
    $dumpfile("uart.vcd");
    $dumpvars(0,test);
end

endmodule
// doesn't receive any outside inputs, but creates all the inputs that the module we want to test requires, 
// then creates an instance of that module

uart.vcd
$date
	Thu Jun 18 15:28:22 2026
$end
$version
	Icarus Verilog
$end
$timescale
	1s
$end
$scope module test $end
$var wire 1 ! uart_tx $end
$var wire 6 " led [5:0] $end
$var reg 1 # btn $end
$var reg 1 $ clk $end
$var reg 1 % uart_rx $end
$scope module u $end
$var wire 1 # btn1 $end
$var wire 1 $ clk $end
$var wire 1 % uart_rx $end
$var wire 1 ! uart_tx $end
$var parameter 8 & DELAY_FRAMES $end
$var parameter 32 ' HALF_DELAY_WAIT $end
$var parameter 32 ( RX_STATE_IDLE $end
$var parameter 32 ) RX_STATE_READ $end
$var parameter 32 * RX_STATE_READ_WAIT $end
$var parameter 32 + RX_STATE_START_BIT $end
$var parameter 32 , RX_STATE_STOP_BIT $end
$var reg 1 - byteReady $end
$var reg 8 . dataIn [7:0] $end
$var reg 6 / led [5:0] $end
$var reg 3 0 rxBitNumber [2:0] $end
$var reg 13 1 rxCounter [12:0] $end
$var reg 4 2 rxState [3:0] $end
$upscope $end
$upscope $end
$enddefinitions $end
$comment Show the parameter values. $end
$dumpall
b101 ,
b1 +
b10 *
b11 )
b0 (
b100 '
b1000 &
$end
#0
$dumpvars
b0 2
b0 1
b0 0
bx /
b0 .
0-
1%
0$
1#
bx "
z!
$end
#1
1$
#2
0$
#3
1$
#4
0$
#5
1$
#6
0$
#7
1$
#8
0$
#9
1$
#10
0$
0%
#11
b1 1
b1 2
1$
#12
0$
#13
b10 1
1$
#14
0$
#15
b11 1
1$
#16
0$
#17
b100 1
1$
#18
0$
#19
b1 1
b10 2
1$
#20
0$
#21
b10 1
1$
#22
0$
#23
b11 1
1$
#24
0$
#25
b100 1
1$
#26
0$
1%
#27
b101 1
1$
#28
0$
#29
b110 1
1$
#30
0$
#31
b111 1
1$
#32
0$
#33
b11 2
b1000 1
1$
#34
0$
#35
b10 2
b1 0
b10000000 .
b1 1
1$
#36
0$
#37
b10 1
1$
#38
0$
#39
b11 1
1$
#40
0$
#41
b100 1
1$
#42
0$
0%
#43
b101 1
1$
#44
0$
#45
b110 1
1$
#46
0$
#47
b111 1
1$
#48
0$
#49
b11 2
b1000 1
1$
#50
0$
#51
b10 2
b10 0
b1000000 .
b1 1
1$
#52
0$
#53
b10 1
1$
#54
0$
#55
b11 1
1$
#56
0$
#57
b100 1
1$
#58
0$
#59
b101 1
1$
#60
0$
#61
b110 1
1$
#62
0$
#63
b111 1
1$
#64
0$
#65
b11 2
b1000 1
1$
#66
0$
#67
b10 2
b11 0
b100000 .
b1 1
1$
#68
0$
#69
b10 1
1$
#70
0$
#71
b11 1
1$
#72
0$
#73
b100 1
1$
#74
0$
#75
b101 1
1$
#76
0$
#77
b110 1
1$
#78
0$
#79
b111 1
1$
#80
0$
#81
b11 2
b1000 1
1$
#82
0$
#83
b10 2
b100 0
b10000 .
b1 1
1$
#84
0$
#85
b10 1
1$
#86
0$
#87
b11 1
1$
#88
0$
#89
b100 1
1$
#90
0$
#91
b101 1
1$
#92
0$
#93
b110 1
1$
#94
0$
#95
b111 1
1$
#96
0$
#97
b11 2
b1000 1
1$
#98
0$
#99
b10 2
b101 0
b1000 .
b1 1
1$
#100
0$
#101
b10 1
1$
#102
0$
#103
b11 1
1$
#104
0$
#105
b100 1
1$
#106
0$
1%
#107
b101 1
1$
#108
0$
#109
b110 1
1$
#110
0$
#111
b111 1
1$
#112
0$
#113
b11 2
b1000 1
1$
#114
0$
#115
b10 2
b110 0
b10000100 .
b1 1
1$
#116
0$
#117
b10 1
1$
#118
0$
#119
b11 1
1$
#120
0$
#121
b100 1
1$
#122
0$
#123
b101 1
1$
#124
0$
#125
b110 1
1$
#126
0$
#127
b111 1
1$
#128
0$
#129
b11 2
b1000 1
1$
#130
0$
#131
b10 2
b111 0
b11000010 .
b1 1
1$
#132
0$
#133
b10 1
1$
#134
0$
#135
b11 1
1$
#136
0$
#137
b100 1
1$
#138
0$
0%
#139
b101 1
1$
#140
0$
#141
b110 1
1$
#142
0$
#143
b111 1
1$
#144
0$
#145
b11 2
b1000 1
1$
#146
0$
#147
b101 2
b0 0
b1100001 .
b1 1
1$
#148
0$
#149
b10 1
1$
#150
0$
#151
b11 1
1$
#152
0$
#153
b100 1
1$
#154
0$
1%
#155
b101 1
1$
#156
0$
#157
b110 1
1$
#158
0$
#159
b111 1
1$
#160
0$
#161
1-
b0 2
b0 1
1$
#162
0$
#163
b11110 "
b11110 /
1$
